<?xml version="1.0" encoding="utf-8"?>
<odoo>
    <!-- Override Login Page Footer -->
    <!-- Note: Title is handled by webclient_templates.xml via web.layout -->
    <template id="login" inherit_id="web.login" name="VumaERP Login Page" priority="999">
        <xpath expr="//footer" position="replace">
            <footer class="text-center text-muted small o_footer o_login_footer pt-3 pb-4">
                <div class="o_footer_content">
                    Powered by <a href="https://vumacloud.com" target="_blank" class="text-muted">VumaCloud</a>
                </div>
            </footer>
        </xpath>
    </template>
</odoo>
